README.md
setup.cfg
setup.py
AlgorithmShare/AlgoShareError.py
AlgorithmShare/__init__.py
AlgorithmShare/client.py
AlgorithmShare.egg-info/PKG-INFO
AlgorithmShare.egg-info/SOURCES.txt
AlgorithmShare.egg-info/dependency_links.txt
AlgorithmShare.egg-info/requires.txt
AlgorithmShare.egg-info/top_level.txt