Metadata-Version: 1.0
Name: AlgorithmShare
Version: 0.0.5
Summary: Intelligent Algorithm Share Framework
Home-page: http://earthdataminer.casearth.cn
Author: qinwei
Author-email: qinwei17@otcaix.iscas.ac.cn
License: UNKNOWN
Platform: UNKNOWN
